autoscab/__init__.py
autoscab/_main.py
autoscab/captchaAudio/.gitignore
autoscab/constants/agents.py
autoscab/constants/classNames.py
autoscab/constants/colors.py
autoscab/constants/common.py
autoscab/constants/elementIds.py
autoscab/constants/email.py
autoscab/constants/fileNames.py
autoscab/constants/location.py
autoscab/constants/parser.py
autoscab/constants/resume.py
autoscab/constants/urls.py
autoscab/constants/uscities.csv
autoscab/constants/xPaths.py
autoscab/deployments/__init__.py
autoscab/deployments/deployment.py
autoscab/deployments/fredmeyer.py
autoscab/deployments/starbucks.py
autoscab/identity/__init__.py
autoscab/identity/identity.py
autoscab/identity/resume.py
autoscab/locators/__init__.py
autoscab/locators/fredmeyer.py
autoscab/locators/locator.py
autoscab/locators/starbucks.py
autoscab/logger.py
autoscab/main.py
autoscab/postbot.py
autoscab/utils.py
autoscab-0.3.2.dist-info/entry_points.txt
autoscab-0.3.2.dist-info/LICENSE
autoscab-0.3.2.dist-info/WHEEL
autoscab-0.3.2.dist-info/METADATA
autoscab-0.3.2.dist-info/RECORD
