Metadata-Version: 2.1
Name: autoscab
Version: 0.3.2
Summary: apply for many of the same job
Home-page: https://github.com/sneakers-the-rat/autoscab
License: Unlicense
Keywords: solidarity,forever
Author: sneakers-the-rat
Requires-Python: >=3.7.1,<4
Classifier: License :: Other/Proprietary License
Classifier: Programming Language :: Python :: 3
Classifier: Programming Language :: Python :: 3.10
Classifier: Programming Language :: Python :: 3.8
Classifier: Programming Language :: Python :: 3.9
Provides-Extra: tests
Requires-Dist: Faker (>=10.0.0,<11.0.0)
Requires-Dist: SpeechRecognition (>=3.8.1,<4.0.0)
Requires-Dist: certifi (>=2021.10.8,<2022.0.0)
Requires-Dist: charset-normalizer (>=2.0.9,<3.0.0)
Requires-Dist: coveralls (>=3.3.1,<4.0.0); extra == "tests"
Requires-Dist: fpdf (>=1.7.2,<2.0.0)
Requires-Dist: idna (>=3.3,<4.0)
Requires-Dist: importlib-metadata (>=4.9.0,<5.0.0); python_version < "3.8"
Requires-Dist: pandas (>=1.3.5,<2.0.0)
Requires-Dist: pdf2image (>=1.16.0,<2.0.0)
Requires-Dist: pydub (>=0.25.1,<0.26.0)
Requires-Dist: pytest (>=6.2.5,<7.0.0); extra == "tests"
Requires-Dist: pytest-cov (>=3.0.0,<4.0.0); extra == "tests"
Requires-Dist: requests (>=2.26.0,<3.0.0)
Requires-Dist: selenium (>=4,<5)
Requires-Dist: typing-extensions (>=4.0.1,<5.0.0); python_version < "3.8"
Requires-Dist: urllib3 (>=1.26.7,<2.0.0)
Requires-Dist: webdriver-manager (>=3.5.2,<4.0.0)
Project-URL: Repository, https://github.com/sneakers-the-rat/autoscab
